LICENSE
MANIFEST.in
Makefile
README.md
setup.cfg
setup.py
Flask_Babeled.egg-info/PKG-INFO
Flask_Babeled.egg-info/SOURCES.txt
Flask_Babeled.egg-info/dependency_links.txt
Flask_Babeled.egg-info/not-zip-safe
Flask_Babeled.egg-info/requires.txt
Flask_Babeled.egg-info/top_level.txt
docs/Makefile
docs/conf.py
docs/index.rst
docs/make.bat
docs/_static/flask-babel.png
flask_babeled/__init__.py
flask_babeled/_compat.py
tests/babel.cfg
tests/tests.py
tests/translations/messages.pot
tests/translations/de/LC_MESSAGES/messages.mo
tests/translations/de/LC_MESSAGES/messages.po