Metadata-Version: 1.1
Name: Flask-Babeled
Version: 0.9.2
Summary: Adds i18n/l10n support to Flask applications
Home-page: http://github.com/jeremyosborne/flask-babeled
Author: Armin Ronacher, Jeremy Osborne
Author-email: armin.ronacher@active-4.com, jeremywosborne@gmail.com
License: BSD
Platform: any
Classifier: Development Status :: 4 - Beta
Classifier: Environment :: Web Environment
Classifier: Intended Audience :: Developers
Classifier: License :: OSI Approved :: BSD License
Classifier: Operating System :: OS Independent
Classifier: Programming Language :: Python
Classifier: Programming Language :: Python :: 3
Classifier: Topic :: Internet :: WWW/HTTP :: Dynamic Content
Classifier: Topic :: Software Development :: Libraries :: Python Modules
